xgboostlss/__init__.py
xgboostlss/model.py
xgboostlss/utils.py
xgboostlss/datasets/__init__.py
xgboostlss/datasets/arcticlake.csv
xgboostlss/datasets/data_loader.py
xgboostlss/datasets/gaussian_test_sim.csv
xgboostlss/datasets/gaussian_train_sim.csv
xgboostlss/datasets/sim_triv_gaussian.csv
xgboostlss/datasets/sim_triv_studentT.csv
xgboostlss/datasets/studentT_test_sim.csv
xgboostlss/datasets/studentT_train_sim.csv
xgboostlss/distributions/Beta.py
xgboostlss/distributions/Cauchy.py
xgboostlss/distributions/Dirichlet.py
xgboostlss/distributions/Expectile.py
xgboostlss/distributions/Gamma.py
xgboostlss/distributions/Gaussian.py
xgboostlss/distributions/Gumbel.py
xgboostlss/distributions/Laplace.py
xgboostlss/distributions/LogNormal.py
xgboostlss/distributions/Logistic.py
xgboostlss/distributions/MVN.py
xgboostlss/distributions/MVN_LoRa.py
xgboostlss/distributions/MVT.py
xgboostlss/distributions/Mixture.py
xgboostlss/distributions/NegativeBinomial.py
xgboostlss/distributions/Poisson.py
xgboostlss/distributions/SplineFlow.py
xgboostlss/distributions/StudentT.py
xgboostlss/distributions/Weibull.py
xgboostlss/distributions/ZABeta.py
xgboostlss/distributions/ZAGamma.py
xgboostlss/distributions/ZALN.py
xgboostlss/distributions/ZINB.py
xgboostlss/distributions/ZIPoisson.py
xgboostlss/distributions/__init__.py
xgboostlss/distributions/distribution_utils.py
xgboostlss/distributions/flow_utils.py
xgboostlss/distributions/mixture_distribution_utils.py
xgboostlss/distributions/multivariate_distribution_utils.py
xgboostlss/distributions/zero_inflated.py
xgboostlss-0.6.1.dist-info/licenses/LICENSE.txt
xgboostlss-0.6.1.dist-info/METADATA
xgboostlss-0.6.1.dist-info/WHEEL
xgboostlss-0.6.1.dist-info/top_level.txt
xgboostlss-0.6.1.dist-info/zip-safe
xgboostlss-0.6.1.dist-info/RECORD
