Metadata-Version: 2.4
Name: xgboostlss
Version: 0.6.1
Summary: XGBoostLSS - An extension of XGBoost to probabilistic modelling
Author-email: Alexander März <statmixedmlgit@gmail.com>
License: Apache License 2.0
Project-URL: Homepage, https://github.com/StatMixedML/XGBoostLSS
Classifier: Intended Audience :: Developers
Classifier: Intended Audience :: Science/Research
Classifier: License :: OSI Approved :: Apache Software License
Classifier: Operating System :: MacOS
Classifier: Operating System :: Microsoft :: Windows
Classifier: Operating System :: POSIX
Classifier: Operating System :: Unix
Classifier: Programming Language :: Python
Classifier: Programming Language :: Python :: 3 :: Only
Classifier: Programming Language :: Python :: 3.11
Classifier: Programming Language :: Python :: 3.12
Classifier: Programming Language :: Python :: 3.13
Classifier: Programming Language :: Python :: 3.14
Classifier: Topic :: Scientific/Engineering
Classifier: Topic :: Scientific/Engineering :: Artificial Intelligence
Classifier: Topic :: Software Development
Requires-Python: >=3.11
License-File: LICENSE.txt
Requires-Dist: xgboost<4.0,>=2.0
Requires-Dist: torch<2.10,>=2.1
Requires-Dist: pyro-ppl<1.10,>=1.8
Requires-Dist: numpy<2.4,>=1.26.0
Requires-Dist: pandas<2.3,>=2.0
Requires-Dist: scipy<1.17,>=1.11
Requires-Dist: tqdm<4.68,>=4.66
Requires-Dist: matplotlib<3.11,>=3.8
Requires-Dist: scikit-base
Provides-Extra: all-extras
Requires-Dist: optuna<4.4,>=3.5.0; extra == "all-extras"
Requires-Dist: optuna-integration; extra == "all-extras"
Requires-Dist: seaborn<0.14.0,>=0.13.0; extra == "all-extras"
Requires-Dist: shap>=0.50.0; python_version < "3.14" and extra == "all-extras"
Provides-Extra: docs
Requires-Dist: mkdocs; extra == "docs"
Requires-Dist: mkdocstrings[python]; extra == "docs"
Requires-Dist: mkdocs-jupyter; extra == "docs"
Provides-Extra: notebooks
Requires-Dist: scikit-learn<1.8.0,>=1.4.0; extra == "notebooks"
Requires-Dist: plotnine<0.16.0,>=0.12.0; extra == "notebooks"
Provides-Extra: test
Requires-Dist: flake8; extra == "test"
Requires-Dist: pytest; extra == "test"
Requires-Dist: pytest-coverage; extra == "test"
Requires-Dist: pytest-timeout; extra == "test"
Dynamic: license-file
